[
    {
        "model": "mosaicaapi.tile",
        "pk": 1,
        "fields": {
            "name": "A1"
        }
    },
    {
        "model": "mosaicaapi.tile",
        "pk": 2,
        "fields": {
            "name": "A2"
        }
    },
    {
        "model": "mosaicaapi.tile",
        "pk": 3,
        "fields": {
            "name": "A3"
        }
    },
    {
        "model": "mosaicaapi.tile",
        "pk": 4,
        "fields": {
            "name": "A4"
        }
    },
    {
        "model": "mosaicaapi.tile",
        "pk": 5,
        "fields": {
            "name": "A5"
        }
    },
    {
        "model": "mosaicaapi.tile",
        "pk": 6,
        "fields": {
            "name": "B1"
        }
    },
    {
        "model": "mosaicaapi.tile",
        "pk": 7,
        "fields": {
            "name": "B2"
        }
    },
    {
        "model": "mosaicaapi.tile",
        "pk": 8,
        "fields": {
            "name": "B3"
        }
    },
    {
        "model": "mosaicaapi.tile",
        "pk": 9,
        "fields": {
            "name": "B4"
        }
    },
    {
        "model": "mosaicaapi.tile",
        "pk": 10,
        "fields": {
            "name": "B5"
        }
    },
    {
        "model": "mosaicaapi.tile",
        "pk": 11,
        "fields": {
            "name": "C1"
        }
    },
    {
        "model": "mosaicaapi.tile",
        "pk": 12,
        "fields": {
            "name": "C2"
        }
    },
    {
        "model": "mosaicaapi.tile",
        "pk": 13,
        "fields": {
            "name": "C3"
        }
    },
    {
        "model": "mosaicaapi.tile",
        "pk": 14,
        "fields": {
            "name": "C4"
        }
    },
    {
        "model": "mosaicaapi.tile",
        "pk": 15,
        "fields": {
            "name": "C5"
        }
    },
    {
        "model": "mosaicaapi.tile",
        "pk": 16,
        "fields": {
            "name": "D1"
        }
    },
    {
        "model": "mosaicaapi.tile",
        "pk": 17,
        "fields": {
            "name": "D2"
        }
    },
    {
        "model": "mosaicaapi.tile",
        "pk": 18,
        "fields": {
            "name": "D3"
        }
    },
    {
        "model": "mosaicaapi.tile",
        "pk": 19,
        "fields": {
            "name": "D4"
        }
    },
    {
        "model": "mosaicaapi.tile",
        "pk": 20,
        "fields": {
            "name": "D5"
        }
    },
    {
        "model": "mosaicaapi.tile",
        "pk": 21,
        "fields": {
            "name": "E1"
        }
    },
    {
        "model": "mosaicaapi.tile",
        "pk": 22,
        "fields": {
            "name": "E2"
        }
    },
    {
        "model": "mosaicaapi.tile",
        "pk": 23,
        "fields": {
            "name": "E3"
        }
    },
    {
        "model": "mosaicaapi.tile",
        "pk": 24,
        "fields": {
            "name": "E4"
        }
    },
    {
        "model": "mosaicaapi.tile",
        "pk": 25,
        "fields": {
            "name": "E5"
        }
    }
]
